nvidia_audio2face_3d_authoring/__init__.py
nvidia_audio2face_3d_authoring/audio2face_3d_authoring_pb2.py
nvidia_audio2face_3d_authoring/audio2face_3d_authoring_pb2.pyi
nvidia_audio2face_3d_authoring/audio2face_3d_authoring_pb2_grpc.py
nvidia_audio2face_3d_authoring/messages_pb2.py
nvidia_audio2face_3d_authoring/messages_pb2.pyi
nvidia_audio2face_3d_authoring/messages_pb2_grpc.py
nvidia_audio2face_3d_authoring/py.typed
nvidia_audio2face_3d_authoring-0.2.0.dist-info/METADATA
nvidia_audio2face_3d_authoring-0.2.0.dist-info/WHEEL
nvidia_audio2face_3d_authoring-0.2.0.dist-info/licenses/LICENSE
nvidia_audio2face_3d_authoring-0.2.0.dist-info/RECORD
